concordia/__init__.py
concordia/concordia_integration_test.py
concordia/agents/__init__.py
concordia/agents/entity_agent.py
concordia/agents/entity_agent_with_logging.py
concordia/agents/deprecated/__init__.py
concordia/agents/deprecated/deprecated_agent.py
concordia/agents/deprecated/entity_agent.py
concordia/agents/deprecated/entity_agent_with_logging.py
concordia/agents/deprecated/factory_entity_agent_with_logging.py
concordia/agents/deprecated/simple_llm_agent.py
concordia/associative_memory/__init__.py
concordia/associative_memory/basic_associative_memory.py
concordia/associative_memory/deprecated/__init__.py
concordia/associative_memory/deprecated/associative_memory.py
concordia/associative_memory/deprecated/blank_memories.py
concordia/associative_memory/deprecated/factory_formative_memories.py
concordia/associative_memory/deprecated/formative_memories.py
concordia/associative_memory/deprecated/importance_function.py
concordia/clocks/__init__.py
concordia/clocks/game_clock.py
concordia/clocks/game_clock_test.py
concordia/components/__init__.py
concordia/components/agent/__init__.py
concordia/components/agent/action_spec_ignored.py
concordia/components/agent/agent_components_test.py
concordia/components/agent/all_similar_memories.py
concordia/components/agent/concat_act_component.py
concordia/components/agent/constant.py
concordia/components/agent/instructions.py
concordia/components/agent/memory.py
concordia/components/agent/no_op_context_processor.py
concordia/components/agent/observation.py
concordia/components/agent/plan.py
concordia/components/agent/question_of_recent_memories.py
concordia/components/agent/report_function.py
concordia/components/agent/scripted_act.py
concordia/components/agent/deprecated/__init__.py
concordia/components/agent/deprecated/action_spec_ignored.py
concordia/components/agent/deprecated/all_similar_memories.py
concordia/components/agent/deprecated/concat_act_component.py
concordia/components/agent/deprecated/constant.py
gdm_concordia-2.1.0.dist-info/LICENSE
gdm_concordia-2.1.0.dist-info/METADATA
gdm_concordia-2.1.0.dist-info/WHEEL
gdm_concordia-2.1.0.dist-info/top_level.txt
gdm_concordia-2.1.0.dist-info/RECORD
