Metadata-Version: 2.1
Name: gdm-concordia
Version: 2.1.0
Summary: A library for building a generative model of social interacions.
Home-page: https://github.com/google-deepmind/concordia
Download-URL: https://github.com/google-deepmind/concordia/releases
Author: DeepMind
Author-email: noreply@google.com
License: Apache 2.0
Keywords: multi-agent agent-based-simulation generative-agents python machine-learning
Classifier: Development Status :: 4 - Beta
Classifier: Intended Audience :: Developers
Classifier: Intended Audience :: Education
Classifier: Intended Audience :: Science/Research
Classifier: License :: OSI Approved :: Apache Software License
Classifier: Operating System :: POSIX :: Linux
Classifier: Operating System :: MacOS :: MacOS X
Classifier: Programming Language :: Python :: 3 :: Only
Classifier: Programming Language :: Python :: 3.11
Classifier: Programming Language :: Python :: 3.12
Classifier: Programming Language :: Python :: 3.13
Classifier: Topic :: Scientific/Engineering :: Artificial Intelligence
Requires-Python: >=3.11
License-File: LICENSE
Requires-Dist: absl-py
Requires-Dist: boto3
Requires-Dist: google-cloud-aiplatform
Requires-Dist: google-generativeai >=0.8
Requires-Dist: ipython
Requires-Dist: jinja2
Requires-Dist: langchain-community
Requires-Dist: matplotlib
Requires-Dist: mistralai
Requires-Dist: numpy >=1.26
Requires-Dist: ollama
Requires-Dist: openai >=1.3.0
Requires-Dist: pandas
Requires-Dist: python-dateutil
Requires-Dist: reactivex
Requires-Dist: retry
Requires-Dist: termcolor
Requires-Dist: together
Requires-Dist: transformers
Requires-Dist: typing-extensions
Provides-Extra: dev
Requires-Dist: build ; extra == 'dev'
Requires-Dist: isort ; extra == 'dev'
Requires-Dist: jupyter ; extra == 'dev'
Requires-Dist: pip-tools ; extra == 'dev'
Requires-Dist: pipreqs ; extra == 'dev'
Requires-Dist: pyink ; extra == 'dev'
Requires-Dist: pylint ; extra == 'dev'
Requires-Dist: pytest-xdist ; extra == 'dev'
Requires-Dist: pytype ; extra == 'dev'
Requires-Dist: twine ; extra == 'dev'
